cosmolopy-0.4.1.dist-info/METADATA
cosmolopy-0.4.1.dist-info/RECORD
cosmolopy-0.4.1.dist-info/WHEEL
cosmolopy-0.4.1.dist-info/top_level.txt
cosmolopy/luminosityfunction.py
cosmolopy/distance.py
cosmolopy/density.py
cosmolopy/parameters.py
cosmolopy/constants.py
cosmolopy/__version__.py
cosmolopy/utils.py
cosmolopy/magnitudes.py
cosmolopy/perturbation.py
cosmolopy/__init__.py
cosmolopy/saveable.py
cosmolopy/reionization.py
cosmolopy/EH/tf_fit.py
cosmolopy/EH/_tf_fit.cpython-38-x86_64-linux-gnu.so
cosmolopy/EH/power.py
cosmolopy/EH/LISCENSE
cosmolopy/EH/_power.cpython-38-x86_64-linux-gnu.so
cosmolopy/EH/__init__.py
