Metadata-Version: 2.1
Name: cosmolopy
Version: 0.4.1
Summary: a cosmology package for Python.
Home-page: http://roban.github.com/CosmoloPy/
Author: Roban Hultman Kramer
Author-email: robanhk@gmail.com
License: MIT
Keywords: astronomy cosmology cosmological distance density galaxyluminosity magnitude reionization Press-Schechter Schecter
Platform: Windows
Platform: Linux
Platform: Unix
Classifier: License :: OSI Approved :: MIT License
Classifier: Programming Language :: Python
Classifier: Programming Language :: Python :: 3
Classifier: Programming Language :: Python :: 3.6
Classifier: Programming Language :: Python :: 3.7
Classifier: Programming Language :: Python :: 3.8
Classifier: Topic :: Scientific/Engineering :: Astronomy
Classifier: Operating System :: OS Independent
Requires-Python: >=3.6, <4
Requires-Dist: numpy (>=1.12.0)
Requires-Dist: scipy (>=1.0.0)
